Orogram-0.6.1.dist-info/WHEEL
Orogram-0.6.1.dist-info/top_level.txt
Orogram-0.6.1.dist-info/RECORD
Orogram-0.6.1.dist-info/LICENSE.txt
Orogram-0.6.1.dist-info/METADATA
orogram/regorofun.cpython-310-x86_64-linux-gnu.so
orogram/xentropy.cpython-310-x86_64-linux-gnu.so
orogram/simplify.cpython-310-x86_64-linux-gnu.so
orogram/orogram.py
orogram/regorogram.py
orogram/credible.cpython-310-x86_64-linux-gnu.so
orogram/bake.cpython-310-x86_64-linux-gnu.so
orogram/util.py
orogram/__init__.py
